{
  "id": "product",
  "label": "Product",
  "format": "custom",
  "repeatable": true,
  "status": true,
  "json": {
    "Main": {
      "uid": {
        "config": {
          "label": "UID"
        },
        "type": "UID"
      },
      "title": {
        "type": "Text",
        "config": {
          "label": "Title",
          "placeholder": ""
        }
      },
      "colllection": {
        "type": "Link",
        "config": {
          "label": "Colllection",
          "select": "document",
          "customtypes": ["collection"]
        }
      },
      "product": {
        "type": "Image",
        "config": {
          "label": "Product",
          "constraint": {},
          "thumbnails": []
        }
      },
      "product2": {
        "type": "Image",
        "config": {
          "label": "Product2",
          "constraint": {},
          "thumbnails": []
        }
      },
      "highlight": {
        "type": "Group",
        "config": {
          "label": "Highlight",
          "fields": {
            "icon": {
              "type": "Select",
              "config": {
                "label": "Icon",
                "placeholder": "",
                "options": ["Arrow", "Star"],
                "default_value": "Arrow"
              }
            },
            "text": {
              "type": "Text",
              "config": {
                "label": "Text",
                "placeholder": ""
              }
            }
          }
        }
      },
      "information": {
        "type": "Group",
        "config": {
          "label": "Information",
          "fields": {
            "label": {
              "type": "Text",
              "config": {
                "label": "Label",
                "placeholder": ""
              }
            },
            "description": {
              "type": "Text",
              "config": {
                "label": "Description",
                "placeholder": ""
              }
            }
          }
        }
      },
      "link_text": {
        "type": "Text",
        "config": {
          "label": "Shop it - Text",
          "placeholder": ""
        }
      },
      "link_url": {
        "type": "Text",
        "config": {
          "label": "Shop it - Link",
          "placeholder": ""
        }
      }
    }
  }
}
